pyspark_root_datasource/__init__.py
pyspark_root_datasource/_utils.py
pyspark_root_datasource/datasource.py
pyspark_root_datasource-0.1.0.dist-info/licenses/LICENSE
pyspark_root_datasource-0.1.0.dist-info/METADATA
pyspark_root_datasource-0.1.0.dist-info/WHEEL
pyspark_root_datasource-0.1.0.dist-info/top_level.txt
pyspark_root_datasource-0.1.0.dist-info/RECORD
