Metadata-Version: 2.4
Name: pyspark-root-datasource
Version: 0.1.0
Summary: Python DataSource for Apache Spark 4 to read ROOT files (High Energy Physics, HEP) as DataFrames, powered by uproot, awkward, and PyArrow
Author-email: Luca Canali <Luca.Canali@cern.ch>
License: Apache-2.0
Project-URL: Homepage, https://github.com/cerndb/pyspark-root-datasource
Project-URL: Repository, https://github.com/cerndb/pyspark-root-datasource
Project-URL: Issues, https://github.com/cerndb/pyspark-root-datasource/issues
Keywords: spark,datasource,root,hep,uproot,awkward,pyarrow,xrootd
Classifier: Development Status :: 3 - Alpha
Classifier: Intended Audience :: Science/Research
Classifier: Intended Audience :: Developers
Classifier: License :: OSI Approved :: Apache Software License
Classifier: Programming Language :: Python :: 3
Classifier: Programming Language :: Python :: 3 :: Only
Classifier: Programming Language :: Python :: 3.9
Classifier: Programming Language :: Python :: 3.10
Classifier: Programming Language :: Python :: 3.11
Classifier: Programming Language :: Python :: 3.12
Classifier: Topic :: Scientific/Engineering
Classifier: Topic :: Software Development :: Libraries
Classifier: Operating System :: OS Independent
Requires-Python: >=3.9
License-File: LICENSE
Requires-Dist: pyspark>=4.0.0
Requires-Dist: uproot>=5.3.0
Requires-Dist: awkward>=2.6.0
Requires-Dist: pyarrow>=15.0.0
Provides-Extra: xrootd
Requires-Dist: fsspec>=2024.3.0; extra == "xrootd"
Requires-Dist: fsspec-xrootd>=0.3.0; extra == "xrootd"
Requires-Dist: XRootD>=5.6.0; extra == "xrootd"
Provides-Extra: dev
Requires-Dist: pytest>=8; extra == "dev"
Requires-Dist: pytest-cov>=5; extra == "dev"
Requires-Dist: ruff>=0.4.0; extra == "dev"
Requires-Dist: black>=24.3.0; extra == "dev"
Requires-Dist: mypy>=1.8.0; extra == "dev"
Requires-Dist: types-setuptools>=69.0.0.0; extra == "dev"
Provides-Extra: test
Requires-Dist: pytest>=8; extra == "test"
Requires-Dist: pytest-cov>=5; extra == "test"
Requires-Dist: pyspark>=4.0.0; extra == "test"
Requires-Dist: uproot>=5.3.0; extra == "test"
Requires-Dist: awkward>=2.6.0; extra == "test"
Requires-Dist: pyarrow>=15.0.0; extra == "test"
Dynamic: license-file
